LICENSE
MANIFEST.in
README.rst
requirements.txt
setup.py
tox.ini
docs/Makefile
docs/conf.py
docs/index.rst
docs/make.bat
docs/user_guide.rst
docs/api/index.rst
docs/api/metas.rst
docs/api/test.rst
docs/api/tools.rst
docs/api/xl.rst
epubaker/__init__.py
epubaker/epub.py
epubaker/epub2.py
epubaker/epub3.py
epubaker/mimes.py
epubaker/tools.py
epubaker/version.py
epubaker.egg-info/PKG-INFO
epubaker.egg-info/SOURCES.txt
epubaker.egg-info/dependency_links.txt
epubaker.egg-info/requires.txt
epubaker.egg-info/top_level.txt
epubaker/metas/__init__.py
epubaker/metas/attrs.py
epubaker/metas/base.py
epubaker/metas/dcmes.py
epubaker/metas/dcterms.py
epubaker/metas/epub2_meta.py
epubaker/metas/epub3_meta.py
epubaker/static/image_page.xhtml
epubaker/static/user_toc_nav.css
epubaker/static/user_toc_nav_fold.js
epubaker/xl/__init__.py
epubaker/xl/xl.py
test/__init__.py
test/test_epub.py
test/cover/cover-canvas.html
test/cover/cover-inkscape.svg
test/cover/cover.jpeg
test/cover/cover.png
test/cover/cover.svg
test/test_xl/__init__.py
test/test_xl/test.xml